setup.cfg
setup.py
worklog/work.py
worklogclitool.egg-info/PKG-INFO
worklogclitool.egg-info/SOURCES.txt
worklogclitool.egg-info/dependency_links.txt
worklogclitool.egg-info/entry_points.txt
worklogclitool.egg-info/requires.txt
worklogclitool.egg-info/top_level.txt