Metadata-Version: 1.0
Name: worklogclitool
Version: 0.1
Summary: A cli tool for loging work hours
Home-page: UNKNOWN
Author: Christoffer Berglund
Author-email: christoffer.berglund.privat@gmail.com
License: UNKNOWN
Keywords: log,work,cli
Platform: UNKNOWN
